pyhud/__init__.py
codehud-0.0.0a0.dist-info/METADATA
codehud-0.0.0a0.dist-info/WHEEL
codehud-0.0.0a0.dist-info/top_level.txt
codehud-0.0.0a0.dist-info/RECORD
